unika_core/__init__.py
unika_core/config.py
unika_core/data_loader.py
unika_core/utils.py
unika_core-0.1.0.dist-info/METADATA
unika_core-0.1.0.dist-info/WHEEL
unika_core-0.1.0.dist-info/top_level.txt
unika_core-0.1.0.dist-info/RECORD
