Metadata-Version: 2.4
Name: unika-core
Version: 0.1.0
Summary: Core utilities for Unika
Requires-Python: >=3.8
